brandizpyes/__init__.py
brandizpyes/ioutils.py
brandizpyes/logging.py
brandizpyes-1.1.1.dist-info/METADATA
brandizpyes-1.1.1.dist-info/WHEEL
brandizpyes-1.1.1.dist-info/licenses/LICENSE
brandizpyes-1.1.1.dist-info/RECORD
