Metadata-Version: 2.4
Name: brandizpyes
Version: 1.1.1
Summary: Brandiz Pyes - Python Utilities
License-Expression: MIT
License-File: LICENSE
Author: Marco Brandizi
Requires-Python: >=3.14
Classifier: Programming Language :: Python :: 3
Classifier: Programming Language :: Python :: 3.14
Requires-Dist: pyyaml (>=6.0.3,<7.0.0)
Project-URL: Changelog, https://github.com/marco-brandizi/brandizpyes/blob/main/CHANGELOG.md
Project-URL: Issues, https://github.com/marco-brandizi/brandizpyes/issues
Project-URL: Repository, https://github.com/marco-brandizi/brandizpyes.git
